justicia/__init__.py
justicia/decision_tree_wrap.py
justicia/dependency_utils.py
justicia/linear_classifier_wrap.py
justicia/metrics.py
justicia/mlic_wrap.py
justicia/poison_attack_wrap.py
justicia/ssat_wrap.py
justicia/subsetsum.py
justicia/utils.py
justicia-0.0.5.dist-info/LICENSE
justicia-0.0.5.dist-info/METADATA
justicia-0.0.5.dist-info/WHEEL
justicia-0.0.5.dist-info/top_level.txt
justicia-0.0.5.dist-info/RECORD
