Metadata-Version: 2.1
Name: justicia
Version: 0.0.5
Summary: This library can be used formally verify machine learning models on multiple fairness definitions.
Home-page: https://github.com/meelgroup/justicia
Download-URL: https://github.com/meelgroup/justicia/archive/v0.0.4.tar.gz
Author: Bishwamittra Ghosh
Author-email: bishwamittra.ghosh@gmail.com
License: MIT
Keywords: ML fairness verification,Application of SSAT solvers
Classifier: Development Status :: 3 - Alpha
Classifier: Intended Audience :: Developers
Classifier: Topic :: Software Development :: Build Tools
Classifier: License :: OSI Approved :: MIT License
Classifier: Programming Language :: Python :: 3.7
License-File: LICENSE
